odoo/addons/account_reconcile_oca/README.rst
odoo/addons/account_reconcile_oca/__init__.py
odoo/addons/account_reconcile_oca/__manifest__.py
odoo/addons/account_reconcile_oca/hooks.py
odoo/addons/account_reconcile_oca/demo/demo.xml
odoo/addons/account_reconcile_oca/i18n/account_reconcile_oca.pot
odoo/addons/account_reconcile_oca/i18n/ca.po
odoo/addons/account_reconcile_oca/i18n/es.po
odoo/addons/account_reconcile_oca/i18n/fr.po
odoo/addons/account_reconcile_oca/i18n/hr.po
odoo/addons/account_reconcile_oca/i18n/it.po
odoo/addons/account_reconcile_oca/i18n/lv.po
odoo/addons/account_reconcile_oca/i18n/nl.po
odoo/addons/account_reconcile_oca/i18n/pt.po
odoo/addons/account_reconcile_oca/i18n/pt_BR.po
odoo/addons/account_reconcile_oca/i18n/ru.po
odoo/addons/account_reconcile_oca/i18n/sv.po
odoo/addons/account_reconcile_oca/i18n/tr.po
odoo/addons/account_reconcile_oca/i18n/zh.po
odoo/addons/account_reconcile_oca/i18n/zh_CN.po
odoo/addons/account_reconcile_oca/models/__init__.py
odoo/addons/account_reconcile_oca/models/account_account_reconcile.py
odoo/addons/account_reconcile_oca/models/account_bank_statement.py
odoo/addons/account_reconcile_oca/models/account_bank_statement_line.py
odoo/addons/account_reconcile_oca/models/account_journal.py
odoo/addons/account_reconcile_oca/models/account_move_line.py
odoo/addons/account_reconcile_oca/models/account_reconcile_abstract.py
odoo/addons/account_reconcile_oca/models/res_company.py
odoo/addons/account_reconcile_oca/models/res_config_settings.py
odoo/addons/account_reconcile_oca/readme/CONTRIBUTORS.md
odoo/addons/account_reconcile_oca/readme/CREDITS.md
odoo/addons/account_reconcile_oca/readme/DESCRIPTION.md
odoo/addons/account_reconcile_oca/readme/ROADMAP.md
odoo/addons/account_reconcile_oca/readme/USAGE.md
odoo/addons/account_reconcile_oca/security/ir.model.access.csv
odoo/addons/account_reconcile_oca/security/security.xml
odoo/addons/account_reconcile_oca/static/description/icon.png
odoo_addon_account_reconcile_oca-18.0.1.1.6.dist-info/METADATA
odoo_addon_account_reconcile_oca-18.0.1.1.6.dist-info/WHEEL
odoo_addon_account_reconcile_oca-18.0.1.1.6.dist-info/top_level.txt
odoo_addon_account_reconcile_oca-18.0.1.1.6.dist-info/RECORD
