Metadata-Version: 2.1
Name: odoo-addon-account_reconcile_oca
Version: 18.0.1.1.6
Requires-Python: >=3.10
Requires-Dist: odoo-addon-account_reconcile_model_oca==18.0.*
Requires-Dist: odoo-addon-account_statement_base==18.0.*
Requires-Dist: odoo==18.0.*
Summary: Reconcile addons for Odoo CE accounting
Home-page: https://github.com/OCA/account-reconcile
License: AGPL-3
Author: CreuBlanca,Dixmit,Odoo Community Association (OCA)
Author-email: support@odoo-community.org
Classifier: Programming Language :: Python
Classifier: Framework :: Odoo
Classifier: Framework :: Odoo :: 18.0
Classifier: License :: OSI Approved :: GNU Affero General Public License v3
